<?xml version="1.0" encoding="utf-8"?>
<TaskRunItem xmlns:xsi="http://www.w3.org/2001/XMLSchema-instance" xmlns:xsd="http://www.w3.org/2001/XMLSchema">
  <Version>1.0</Version>
  <TaskID>10</TaskID>
  <CategroyName><![CDATA[news]]></CategroyName>
  <TaskName><![CDATA[news.qq.com]]></TaskName>
  <DownFilePath><![CDATA[C:\Users\CZB\Desktop\kingkoo1985-NETSpider-master\NETSpider\source\NETSpider\bin\Debug\Config\data]]></DownFilePath>
  <LoginFlag>false</LoginFlag>
  <LoginUrl><![CDATA[]]></LoginUrl>
  <WebCookie><![CDATA[]]></WebCookie>
  <WebEncode>AUTO</WebEncode>
  <UrlEncode>AUTO</UrlEncode>
  <Remark><![CDATA[]]></Remark>
  <WaitMinutes>1</WaitMinutes>
  <WaitUrlCount>0</WaitUrlCount>
  <UrlCount>1</UrlCount>
  <DownFileQueue>true</DownFileQueue>
  <TaskType>Normal</TaskType>
  <ExcuteType>GetOnly</ExcuteType>
  <IsAjax>false</IsAjax>
  <ThreadNum>3</ThreadNum>
  <TryAgainCount>3</TryAgainCount>
  <TryAgainFlag>true</TryAgainFlag>
  <AutoLog>false</AutoLog>
  <AutoErrorLog>false</AutoErrorLog>
  <TempUrl><![CDATA[http://news.qq.com/newsgn/rss_newsgn.xml]]></TempUrl>
  <LastStartPos><![CDATA[]]></LastStartPos>
  <LastEndPos><![CDATA[]]></LastEndPos>
  <UrlList>
    <TaskItemUrl>
      <MainUrl><![CDATA[http://news.qq.com/newsgn/rss_newsgn.xml]]></MainUrl>
      <UrlCount>0</UrlCount>
      <NextPageFlag>false</NextPageFlag>
      <NextPageText><![CDATA[]]></NextPageText>
      <LevelCount>0</LevelCount>
      <NavigateFlag>false</NavigateFlag>
      <LevelUrlList />
      <StartPos><![CDATA[]]></StartPos>
      <EndPos><![CDATA[]]></EndPos>
    </TaskItemUrl>
  </UrlList>
  <ColumnItemList>
    <TaskColumnItem>
      <DataFileType>Text</DataFileType>
      <DataTextType><![CDATA[标题]]></DataTextType>
      <StartPos><![CDATA[<title>]]></StartPos>
      <EndPos><![CDATA[</title>]]></EndPos>
      <LimitSign>LimitSign1</LimitSign>
      <LimitSignText><![CDATA[]]></LimitSignText>
      <ExportLimit>ExportLimit1</ExportLimit>
      <ExportLimitText><![CDATA[]]></ExportLimitText>
      <LimitSignSpaceFlag>false</LimitSignSpaceFlag>
      <ExportLimitSpaceFlag>false</ExportLimitSpaceFlag>
    </TaskColumnItem>
    <TaskColumnItem>
      <DataFileType>Text</DataFileType>
      <DataTextType><![CDATA[链接]]></DataTextType>
      <StartPos><![CDATA[<link>]]></StartPos>
      <EndPos><![CDATA[</link>]]></EndPos>
      <LimitSign>LimitSign1</LimitSign>
      <LimitSignText><![CDATA[]]></LimitSignText>
      <ExportLimit>ExportLimit1</ExportLimit>
      <ExportLimitText><![CDATA[]]></ExportLimitText>
      <LimitSignSpaceFlag>true</LimitSignSpaceFlag>
      <ExportLimitSpaceFlag>true</ExportLimitSpaceFlag>
    </TaskColumnItem>
    <TaskColumnItem>
      <DataFileType>Text</DataFileType>
      <DataTextType><![CDATA[来源]]></DataTextType>
      <StartPos><![CDATA[<author>]]></StartPos>
      <EndPos><![CDATA[</author>]]></EndPos>
      <LimitSign>LimitSign1</LimitSign>
      <LimitSignText><![CDATA[]]></LimitSignText>
      <ExportLimit>ExportLimit1</ExportLimit>
      <ExportLimitText><![CDATA[]]></ExportLimitText>
      <LimitSignSpaceFlag>true</LimitSignSpaceFlag>
      <ExportLimitSpaceFlag>true</ExportLimitSpaceFlag>
    </TaskColumnItem>
    <TaskColumnItem>
      <DataFileType>Text</DataFileType>
      <DataTextType><![CDATA[发布日期]]></DataTextType>
      <StartPos><![CDATA[<pubDate>]]></StartPos>
      <EndPos><![CDATA[</pubDate>]]></EndPos>
      <LimitSign>LimitSign1</LimitSign>
      <LimitSignText><![CDATA[]]></LimitSignText>
      <ExportLimit>ExportLimit1</ExportLimit>
      <ExportLimitText><![CDATA[]]></ExportLimitText>
      <LimitSignSpaceFlag>true</LimitSignSpaceFlag>
      <ExportLimitSpaceFlag>true</ExportLimitSpaceFlag>
    </TaskColumnItem>
    <TaskColumnItem>
      <DataFileType>Text</DataFileType>
      <DataTextType><![CDATA[详情]]></DataTextType>
      <StartPos><![CDATA[<description>]]></StartPos>
      <EndPos><![CDATA[</description>]]></EndPos>
      <LimitSign>LimitSign1</LimitSign>
      <LimitSignText><![CDATA[]]></LimitSignText>
      <ExportLimit>ExportLimit1</ExportLimit>
      <ExportLimitText><![CDATA[]]></ExportLimitText>
      <LimitSignSpaceFlag>true</LimitSignSpaceFlag>
      <ExportLimitSpaceFlag>true</ExportLimitSpaceFlag>
    </TaskColumnItem>
  </ColumnItemList>
  <ConnectionType>None</ConnectionType>
  <ConnectionString><![CDATA[]]></ConnectionString>
  <PubWebCookie><![CDATA[]]></PubWebCookie>
  <PubDataTable><![CDATA[]]></PubDataTable>
  <PubSql><![CDATA[]]></PubSql>
  <PubEncode>AUTO</PubEncode>
  <TriggerType>None</TriggerType>
  <TaskPlanItemList />
  <TaskTempName><![CDATA[news.qq.com635828463708942062]]></TaskTempName>
  <TrueCount>1</TrueCount>
  <ErrorCount>0</ErrorCount>
  <TotalCount>1</TotalCount>
  <ParentTaskTempName><![CDATA[]]></ParentTaskTempName>
  <GaterherState>Completed</GaterherState>
  <GatherUrlItemCompleteList>
    <cGatherUrlItem>
      <Url>http://news.qq.com/newsgn/rss_newsgn.xml</Url>
      <GaterherFlag>Completed</GaterherFlag>
      <Level>0</Level>
      <LevelUrlList />
      <NextPageText />
      <StartPos />
      <EndPos />
    </cGatherUrlItem>
  </GatherUrlItemCompleteList>
  <GatherUrlItemTempList />
  <GatherFileItemCompleteList />
  <GatherFileItemTempList />
</TaskRunItem>